ufro_uhi_plot/__init__.py
ufro_uhi_plot/_nbdev.py
ufro_uhi_plot/map.py
ufro_uhi_plot/uhi.py
ufro_uhi_plot-0.0.2.dist-info/LICENSE
ufro_uhi_plot-0.0.2.dist-info/METADATA
ufro_uhi_plot-0.0.2.dist-info/WHEEL
ufro_uhi_plot-0.0.2.dist-info/entry_points.txt
ufro_uhi_plot-0.0.2.dist-info/top_level.txt
ufro_uhi_plot-0.0.2.dist-info/RECORD
