Metadata-Version: 2.1
Name: ufro-uhi-plot
Version: 0.0.2
Summary: Python proyect to plotting urban heat island.
Home-page: https://github.com/raguileoam/ufro_uhi_plot/tree/master/
Author: raguileoam
Author-email: raguileoam@gmail.com
License: Apache Software License 2.0
Keywords: heat_island uhi
Platform: UNKNOWN
Classifier: Development Status :: 3 - Alpha
Classifier: Intended Audience :: Developers
Classifier: License :: OSI Approved :: Apache Software License
Classifier: Natural Language :: English
Classifier: Programming Language :: Python :: 3.6
Classifier: Programming Language :: Python :: 3.7
Classifier: Programming Language :: Python :: 3.8
Requires-Python: >=3.6
License-File: LICENSE
Requires-Dist: matplotlib
Requires-Dist: numpy
Requires-Dist: pandas
Requires-Dist: matplotlib-scalebar
Requires-Dist: shapely
Requires-Dist: cartopy (>=0.17.0)
Requires-Dist: scipy
